{
    "UserAgent": "aws-amplify-cli/2.0",
    "Version": "1.0",
    "api": {
        "plugins": {
            "awsAPIPlugin": {
                "template": {
                    "endpointType": "GraphQL",
                    "endpoint": "https://tmlbxx3ambgxrny3bubuss2rrm.appsync-api.us-east-1.amazonaws.com/graphql",
                    "region": "us-east-1",
                    "authorizationType": "API_KEY",
                    "apiKey": "da2-lvk7unb2dndabghoixhzndvieu"
                }
            }
        }
    },
    "storage": {
        "plugins": {
            "awsS3StoragePlugin": {
                "bucket": "amplify-headless-s3233736-dev",
                "region": "us-east-1",
                "defaultAccessLevel": "guest"
            }
        }
    }
}